{
  "pools": [
    {
      "rolls": 1,
      "entries": [
        {
          "type": "minecraft:item",
          "name": "minecraft:potion",
          "weight": 4,
          "functions": [
            {
              "function": "minecraft:set_components",
              "components": {
                "minecraft:potion_contents": { "potion": "minecraft:weakness" },
                "minecraft:custom_data": { "pixelburen": { "event": "fishing_karma" } },
                "minecraft:tooltip_display": { "hide_tooltip": true }
              }
            }
          ]
        },
        {
          "type": "minecraft:loot_table",
          "value": "pixelburen:fishing/event/experience_swarm",
          "weight": 3
        },
        {
          "type": "minecraft:empty",
          "weight": 93
        }
      ]
    },
    {
      "rolls": 1,
      "entries": [
        {
          "type": "minecraft:item",
          "name": "minecraft:potion",
          "weight": -3,
          "quality": 1,
          "functions": [
            {
              "function": "minecraft:set_components",
              "components": {
                "minecraft:potion_contents": { "potion": "minecraft:luck" },
                "minecraft:custom_data": { "pixelburen": { "event": "too_lucky" } },
                "minecraft:tooltip_display": { "hide_tooltip": true }
              }
            }
          ]
        }
      ]
    }
  ]
}
